[{"word":"that","freq":31,"score":300,"flags":"bc","syllables":"1"},{"word":"sat","freq":24,"score":300,"flags":"bc","syllables":"1"},{"word":"fat","freq":23,"score":300,"flags":"bc","syllables":"1"},{"word":"cat","freq":22,"score":300,"flags":"bc","syllables":"1"},{"word":"hat","freq":22,"score":300,"flags":"bc","syllables":"1"},{"word":"rat","freq":22,"score":300,"flags":"bc","syllables":"1"},{"word":"bat","freq":20,"score":300,"flags":"bc","syllables":"1"},{"word":"chat","freq":20,"score":300,"flags":"bc","syllables":"1"},{"word":"mat","freq":20,"score":300,"flags":"bc","syllables":"1"},{"word":"pat","freq":19,"score":300,"flags":"bc","syllables":"1"},{"word":"tat","freq":18,"score":300,"flags":"bc","syllables":"1"},{"word":"vat","freq":18,"score":300,"flags":"bc","syllables":"1"},{"word":"flat","freq":23,"score":300,"flags":"bc","syllables":"1"},{"word":"spat","freq":19,"score":300,"flags":"bc","syllables":"1"},{"word":"stat","freq":18,"score":300,"flags":"bc","syllables":"1"},{"word":"caveat","freq":18,"score":300,"flags":"bc","syllables":"3"},{"word":"habitat","freq":20,"score":300,"flags":"bc","syllables":"3"},{"word":"diplomat","freq":19,"score":300,"flags":"bc","syllables":"3"},{"word":"democrat","freq":18,"score":300,"flags":"bc","syllables":"3"},{"word":"thermostat","freq":18,"score":300,"flags":"bc","syllables":"3"},{"word":"aristocrat","freq":18,"score":300,"flags":"bc","syllables":"4"},{"word":"add","freq":24,"score":264,"flags":"bc","syllables":"1"},{"word":"ad","freq":23,"score":264,"flags":"bc","syllables":"1"},{"word":"had","freq":29,"score":264,"flags":"bc","syllables":"1"},{"word":"bad","freq":24,"score":264,"flags":"bc","syllables":"1"},{"word":"catch","freq":23,"score":264,"flags":"bc","syllables":"1"},{"word":"map","freq":23,"score":264,"flags":"bc","syllables":"1"},{"word":"cap","freq":22,"score":264,"flags":"bc","syllables":"1"},{"word":"gap","freq":22,"score":264,"flags":"bc","syllables":"1"},{"word":"mad","freq":22,"score":264,"flags":"bc","syllables":"1"},{"word":"match","freq":22,"score":264,"flags":"bc","syllables":"1"},{"word":"sad","freq":22,"score":264,"flags":"bc","syllables":"1"},{"word":"chap","freq":21,"score":264,"flags":"bc","syllables":"1"},{"word":"lad","freq":21,"score":264,"flags":"bc","syllables":"1"},{"word":"lap","freq":21,"score":264,"flags":"bc","syllables":"1"},{"word":"patch","freq":21,"score":264,"flags":"bc","syllables":"1"},{"word":"tap","freq":21,"score":264,"flags":"bc","syllables":"1"},{"word":"batch","freq":20,"score":264,"flags":"bc","syllables":"1"},{"word":"cab","freq":20,"score":264,"flags":"bc","syllables":"1"},{"word":"dad","freq":20,"score":264,"flags":"bc","syllables":"1"},{"word":"lab","freq":20,"score":264,"flags":"bc","syllables":"1"},{"word":"pad","freq":20,"score":264,"flags":"bc","syllables":"1"},{"word":"tab","freq":20,"score":264,"flags":"bc","syllables":"1"},{"word":"wrap","freq":20,"score":264,"flags":"bc","syllables":"1"},{"word":"badge","freq":19,"score":264,"flags":"bc","syllables":"1"},{"word":"hatch","freq":19,"score":264,"flags":"bc","syllables":"1"},{"word":"latch","freq":19,"score":264,"flags":"bc","syllables":"1"},{"word":"nap","freq":19,"score":264,"flags":"bc","syllables":"1"},{"word":"rap","freq":19,"score":264,"flags":"bc","syllables":"1"},{"word":"sap","freq":19,"score":264,"flags":"bc","syllables":"1"},{"word":"fad","freq":18,"score":264,"flags":"bc","syllables":"1"},{"word":"rad","freq":18,"score":264,"flags":"bc","syllables":"1"},{"word":"thatch","freq":18,"score":264,"flags":"bc","syllables":"1"},{"word":"glad","freq":23,"score":264,"flags":"bc","syllables":"1"},{"word":"attach","freq":21,"score":264,"flags":"bc","syllables":"2"},{"word":"trap","freq":21,"score":264,"flags":"bc","syllables":"1"},{"word":"clad","freq":20,"score":264,"flags":"bc","syllables":"1"},{"word":"flap","freq":20,"score":264,"flags":"bc","syllables":"1"},{"word":"grab","freq":20,"score":264,"flags":"bc","syllables":"1"},{"word":"slab","freq":20,"score":264,"flags":"bc","syllables":"1"},{"word":"snap","freq":20,"score":264,"flags":"bc","syllables":"1"},{"word":"crab","freq":19,"score":264,"flags":"bc","syllables":"1"},{"word":"slap","freq":19,"score":264,"flags":"bc","syllables":"1"},{"word":"snatch","freq":19,"score":264,"flags":"bc","syllables":"1"},{"word":"stab","freq":19,"score":264,"flags":"bc","syllables":"1"},{"word":"clap","freq":18,"score":264,"flags":"bc","syllables":"1"},{"word":"crap","freq":18,"score":264,"flags":"bc","syllables":"1"},{"word":"drab","freq":18,"score":264,"flags":"bc","syllables":"1"},{"word":"plaid","freq":18,"score":264,"flags":"bc","syllables":"1"},{"word":"scrap","freq":20,"score":264,"flags":"bc","syllables":"1"},{"word":"scratch","freq":20,"score":264,"flags":"bc","syllables":"1"},{"word":"strap","freq":19,"score":264,"flags":"bc","syllables":"1"},{"word":"detach","freq":18,"score":264,"flags":"bc","syllables":"2"},{"word":"overlap","freq":21,"score":264,"flags":"bc","syllables":"3"},{"word":"dispatch","freq":20,"score":264,"flags":"bc","syllables":"2"},{"word":"mismatch","freq":18,"score":264,"flags":"bc","syllables":"2"},{"word":"handicap","freq":20,"score":264,"flags":"bc","syllables":"3"},{"word":"act","freq":25,"score":228,"flags":"bc","syllables":"1"},{"word":"apt","freq":22,"score":228,"flags":"bc","syllables":"1"},{"word":"aunt","freq":21,"score":228,"flags":"bc","syllables":"1"},{"word":"ant","freq":20,"score":228,"flags":"bc","syllables":"1"},{"word":"aft","freq":19,"score":228,"flags":"bc","syllables":"1"},{"word":"fact","freq":26,"score":228,"flags":"bc","syllables":"1"},{"word":"last","freq":26,"score":228,"flags":"bc","syllables":"1"},{"word":"asked","freq":25,"score":228,"flags":"bc","syllables":"1"},{"word":"passed","freq":25,"score":228,"flags":"bc","syllables":"1"},{"word":"past","freq":25,"score":228,"flags":"bc","syllables":"1"},{"word":"fast","freq":24,"score":228,"flags":"bc","syllables":"1"},{"word":"cast","freq":23,"score":228,"flags":"bc","syllables":"1"},{"word":"vast","freq":23,"score":228,"flags":"bc","syllables":"1"},{"word":"laughed","freq":22,"score":228,"flags":"bc","syllables":"1"},{"word":"packed","freq":22,"score":228,"flags":"bc","syllables":"1"},{"word":"shaft","freq":22,"score":228,"flags":"bc","syllables":"1"},{"word":"backed","freq":21,"score":228,"flags":"bc","syllables":"1"},{"word":"caste","freq":21,"score":228,"flags":"bc","syllables":"1"},{"word":"dashed","freq":21,"score":228,"flags":"bc","syllables":"1"},{"word":"hast","freq":21,"score":228,"flags":"bc","syllables":"1"},{"word":"lacked","freq":21,"score":228,"flags":"bc","syllables":"1"},{"word":"matched","freq":21,"score":228,"flags":"bc","syllables":"1"},{"word":"wrapped","freq":21,"score":228,"flags":"bc","syllables":"1"},{"word":"mapped","freq":20,"score":228,"flags":"bc","syllables":"1"},{"word":"mast","freq":20,"score":228,"flags":"bc","syllables":"1"},{"word":"pact","freq":20,"score":228,"flags":"bc","syllables":"1"},{"word":"shalt","freq":20,"score":228,"flags":"bc","syllables":"1"},{"word":"tact","freq":20,"score":228,"flags":"bc","syllables":"1"},{"word":"tapped","freq":20,"score":228,"flags":"bc","syllables":"1"},{"word":"cant","freq":19,"score":228,"flags":"bc","syllables":"1"},{"word":"capped","freq":19,"score":228,"flags":"bc","syllables":"1"},{"word":"chant","freq":19,"score":228,"flags":"bc","syllables":"1"},{"word":"hatched","freq":19,"score":228,"flags":"bc","syllables":"1"},{"word":"lashed","freq":19,"score":228,"flags":"bc","syllables":"1"},{"word":"raft","freq":19,"score":228,"flags":"bc","syllables":"1"},{"word":"thatched","freq":19,"score":228,"flags":"bc","syllables":"1"},{"word":"hacked","freq":18,"score":228,"flags":"bc","syllables":"1"},{"word":"mashed","freq":18,"score":228,"flags":"bc","syllables":"1"},{"word":"plant","freq":24,"score":228,"flags":"bc","syllables":"1"},{"word":"attached","freq":23,"score":228,"flags":"bc","syllables":"2"},{"word":"attacked","freq":23,"score":228,"flags":"bc","syllables":"2"},{"word":"grant","freq":23,"score":228,"flags":"bc","syllables":"1"},{"word":"craft","freq":22,"score":228,"flags":"bc","syllables":"1"},{"word":"draft","freq":22,"score":228,"flags":"bc","syllables":"1"},{"word":"tract","freq":22,"score":228,"flags":"bc","syllables":"1"},{"word":"adapt","freq":21,"score":228,"flags":"bc","syllables":"2"},{"word":"blast","freq":21,"score":228,"flags":"bc","syllables":"1"},{"word":"graft","freq":21,"score":228,"flags":"bc","syllables":"1"},{"word":"react","freq":21,"score":228,"flags":"bc","syllables":"2"},{"word":"trapped","freq":21,"score":228,"flags":"bc","syllables":"1"},{"word":"classed","freq":20,"score":228,"flags":"bc","syllables":"1"},{"word":"cracked","freq":20,"score":228,"flags":"bc","syllables":"1"},{"word":"danced","freq":20,"score":228,"flags":"bc","syllables":"1"},{"word":"draught","freq":20,"score":228,"flags":"bc","syllables":"1"},{"word":"flashed","freq":20,"score":228,"flags":"bc","syllables":"1"},{"word":"ranked","freq":20,"score":228,"flags":"bc","syllables":"1"},{"word":"snapped","freq":20,"score":228,"flags":"bc","syllables":"1"},{"word":"snatched","freq":20,"score":228,"flags":"bc","syllables":"1"},{"word":"taxed","freq":20,"score":228,"flags":"bc","syllables":"1"},{"word":"thanked","freq":20,"score":228,"flags":"bc","syllables":"1"},{"word":"camped","freq":19,"score":228,"flags":"bc","syllables":"1"},{"word":"clapped","freq":19,"score":228,"flags":"bc","syllables":"1"},{"word":"crashed","freq":19,"score":228,"flags":"bc","syllables":"1"},{"word":"enact","freq":19,"score":228,"flags":"bc","syllables":"2"},{"word":"gasped","freq":19,"score":228,"flags":"bc","syllables":"1"},{"word":"harassed","freq":19,"score":228,"flags":"bc","syllables":"2"},{"word":"masked","freq":19,"score":228,"flags":"bc","syllables":"1"},{"word":"scant","freq":19,"score":228,"flags":"bc","syllables":"1"},{"word":"slant","freq":19,"score":228,"flags":"bc","syllables":"1"},{"word":"slapped","freq":19,"score":228,"flags":"bc","syllables":"1"},{"word":"smashed","freq":19,"score":228,"flags":"bc","syllables":"1"},{"word":"stacked","freq":19,"score":228,"flags":"bc","syllables":"1"},{"word":"staffed","freq":19,"score":228,"flags":"bc","syllables":"1"},{"word":"tracked","freq":19,"score":228,"flags":"bc","syllables":"1"},{"word":"waxed","freq":19,"score":228,"flags":"bc","syllables":"1"},{"word":"impact","freq":24,"score":228,"flags":"bc","syllables":"2"},{"word":"exact","freq":23,"score":228,"flags":"bc","syllables":"2"},{"word":"attract","freq":22,"score":228,"flags":"bc","syllables":"2"},{"word":"detached","freq":21,"score":228,"flags":"bc","syllables":"2"},{"word":"glanced","freq":21,"score":228,"flags":"bc","syllables":"1"},{"word":"grasped","freq":21,"score":228,"flags":"bc","syllables":"1"},{"word":"intact","freq":21,"score":228,"flags":"bc","syllables":"2"},{"word":"elapsed","freq":20,"score":228,"flags":"bc","syllables":"2"},{"word":"stamped","freq":20,"score":228,"flags":"bc","syllables":"1"},{"word":"surpassed","freq":20,"score":228,"flags":"bc","syllables":"2"},{"word":"branched","freq":19,"score":228,"flags":"bc","syllables":"1"},{"word":"clamped","freq":19,"score":228,"flags":"bc","syllables":"1"},{"word":"clasped","freq":19,"score":228,"flags":"bc","syllables":"1"},{"word":"cramped","freq":19,"score":228,"flags":"bc","syllables":"1"},{"word":"flanked","freq":19,"score":228,"flags":"bc","syllables":"1"},{"word":"scratched","freq":19,"score":228,"flags":"bc","syllables":"1"},{"word":"advanced","freq":24,"score":228,"flags":"bc","syllables":"2"},{"word":"enhanced","freq":22,"score":228,"flags":"bc","syllables":"2"},{"word":"collapsed","freq":21,"score":228,"flags":"bc","syllables":"2"},{"word":"interact","freq":21,"score":228,"flags":"bc","syllables":"3"},{"word":"relaxed","freq":21,"score":228,"flags":"bc","syllables":"2"},{"word":"dispatched","freq":20,"score":228,"flags":"bc","syllables":"2"},{"word":"financed","freq":20,"score":228,"flags":"bc","syllables":"2"},{"word":"encamped","freq":19,"score":228,"flags":"bc","syllables":"2"},{"word":"implant","freq":19,"score":228,"flags":"bc","syllables":"2"},{"word":"abstract","freq":23,"score":228,"flags":"bc","syllables":"2"},{"word":"extract","freq":22,"score":228,"flags":"bc","syllables":"2"},{"word":"counteract","freq":20,"score":228,"flags":"bc","syllables":"3"},{"word":"artifact","freq":19,"score":228,"flags":"bc","syllables":"3"},{"word":"distract","freq":19,"score":228,"flags":"bc","syllables":"2"},{"word":"subtract","freq":19,"score":228,"flags":"bc","syllables":"2"},{"word":"handicapped","freq":20,"score":228,"flags":"bc","syllables":"3"},{"word":"photographed","freq":19,"score":228,"flags":"bc","syllables":"3"},{"word":"transplant","freq":20,"score":228,"flags":"bc","syllables":"2"},{"word":"hand","freq":26,"score":192,"flags":"bc","syllables":"1"},{"word":"land","freq":26,"score":192,"flags":"bc","syllables":"1"},{"word":"band","freq":23,"score":192,"flags":"bc","syllables":"1"},{"word":"camp","freq":23,"score":192,"flags":"bc","syllables":"1"},{"word":"sand","freq":23,"score":192,"flags":"bc","syllables":"1"},{"word":"lamp","freq":22,"score":192,"flags":"bc","syllables":"1"},{"word":"damp","freq":21,"score":192,"flags":"bc","syllables":"1"},{"word":"banned","freq":20,"score":192,"flags":"bc","syllables":"1"},{"word":"damned","freq":20,"score":192,"flags":"bc","syllables":"1"},{"word":"hanged","freq":20,"score":192,"flags":"bc","syllables":"1"},{"word":"ranch","freq":20,"score":192,"flags":"bc","syllables":"1"},{"word":"canned","freq":19,"score":192,"flags":"bc","syllables":"1"},{"word":"jagged","freq":19,"score":192,"flags":"bc","syllables":"1"},{"word":"jammed","freq":19,"score":192,"flags":"bc","syllables":"1"},{"word":"lagged","freq":19,"score":192,"flags":"bc","syllables":"1"},{"word":"manned","freq":19,"score":192,"flags":"bc","syllables":"1"},{"word":"ramp","freq":19,"score":192,"flags":"bc","syllables":"1"},{"word":"stand","freq":24,"score":192,"flags":"bc","syllables":"1"},{"word":"branch","freq":23,"score":192,"flags":"bc","syllables":"1"},{"word":"grand","freq":23,"score":192,"flags":"bc","syllables":"1"},{"word":"planned","freq":23,"score":192,"flags":"bc","syllables":"1"},{"word":"grasp","freq":22,"score":192,"flags":"bc","syllables":"1"},{"word":"brand","freq":21,"score":192,"flags":"bc","syllables":"1"},{"word":"dragged","freq":21,"score":192,"flags":"bc","syllables":"1"},{"word":"gland","freq":21,"score":192,"flags":"bc","syllables":"1"},{"word":"grabbed","freq":21,"score":192,"flags":"bc","syllables":"1"},{"word":"stamp","freq":21,"score":192,"flags":"bc","syllables":"1"},{"word":"scalp","freq":20,"score":192,"flags":"bc","syllables":"1"},{"word":"bland","freq":19,"score":192,"flags":"bc","syllables":"1"},{"word":"clamp","freq":19,"score":192,"flags":"bc","syllables":"1"},{"word":"clasp","freq":19,"score":192,"flags":"bc","syllables":"1"},{"word":"crammed","freq":19,"score":192,"flags":"bc","syllables":"1"},{"word":"flange","freq":19,"score":192,"flags":"bc","syllables":"1"},{"word":"scanned","freq":19,"score":192,"flags":"bc","syllables":"1"},{"word":"slammed","freq":19,"score":192,"flags":"bc","syllables":"1"},{"word":"stabbed","freq":19,"score":192,"flags":"bc","syllables":"1"},{"word":"tramp","freq":19,"score":192,"flags":"bc","syllables":"1"},{"word":"command","freq":24,"score":192,"flags":"bc","syllables":"2"},{"word":"demand","freq":24,"score":192,"flags":"bc","syllables":"2"},{"word":"strand","freq":20,"score":192,"flags":"bc","syllables":"1"},{"word":"expand","freq":22,"score":192,"flags":"bc","syllables":"2"},{"word":"avalanche","freq":19,"score":192,"flags":"bc","syllables":"3"},{"word":"overland","freq":19,"score":192,"flags":"bc","syllables":"3"},{"word":"withstand","freq":20,"score":192,"flags":"bc","syllables":"2"},{"word":"understand","freq":25,"score":192,"flags":"bc","syllables":"3"},{"word":"hinterland","freq":19,"score":192,"flags":"bc","syllables":"3"},{"word":"contraband","freq":19,"score":192,"flags":"bc","syllables":"3"},{"word":"not","freq":30,"score":156,"flags":"bc","syllables":"1"},{"word":"but","freq":29,"score":156,"flags":"bc","syllables":"1"},{"word":"what","freq":28,"score":156,"flags":"bc","syllables":"1"},{"word":"cut","freq":25,"score":156,"flags":"bc","syllables":"1"},{"word":"got","freq":25,"score":156,"flags":"bc","syllables":"1"},{"word":"hot","freq":24,"score":156,"flags":"bc","syllables":"1"},{"word":"lot","freq":24,"score":156,"flags":"bc","syllables":"1"},{"word":"bought","freq":23,"score":156,"flags":"bc","syllables":"1"},{"word":"caught","freq":23,"score":156,"flags":"bc","syllables":"1"},{"word":"shot","freq":23,"score":156,"flags":"bc","syllables":"1"},{"word":"hurt","freq":22,"score":156,"flags":"bc","syllables":"1"},{"word":"pot","freq":22,"score":156,"flags":"bc","syllables":"1"},{"word":"shirt","freq":22,"score":156,"flags":"bc","syllables":"1"},{"word":"shut","freq":22,"score":156,"flags":"bc","syllables":"1"},{"word":"dirt","freq":21,"score":156,"flags":"bc","syllables":"1"},{"word":"hut","freq":21,"score":156,"flags":"bc","syllables":"1"},{"word":"butt","freq":20,"score":156,"flags":"bc","syllables":"1"},{"word":"dot","freq":20,"score":156,"flags":"bc","syllables":"1"},{"word":"gut","freq":20,"score":156,"flags":"bc","syllables":"1"},{"word":"knot","freq":20,"score":156,"flags":"bc","syllables":"1"},{"word":"nut","freq":20,"score":156,"flags":"bc","syllables":"1"},{"word":"rot","freq":20,"score":156,"flags":"bc","syllables":"1"},{"word":"cot","freq":19,"score":156,"flags":"bc","syllables":"1"},{"word":"tot","freq":19,"score":156,"flags":"bc","syllables":"1"},{"word":"yacht","freq":19,"score":156,"flags":"bc","syllables":"1"},{"word":"plot","freq":23,"score":156,"flags":"bc","syllables":"1"},{"word":"spot","freq":23,"score":156,"flags":"bc","syllables":"1"},{"word":"assert","freq":22,"score":156,"flags":"bc","syllables":"2"},{"word":"alert","freq":21,"score":156,"flags":"bc","syllables":"2"},{"word":"overt","freq":21,"score":156,"flags":"bc","syllables":"2"},{"word":"inert","freq":20,"score":156,"flags":"bc","syllables":"2"},{"word":"skirt","freq":20,"score":156,"flags":"bc","syllables":"1"},{"word":"slot","freq":20,"score":156,"flags":"bc","syllables":"1"},{"word":"avert","freq":19,"score":156,"flags":"bc","syllables":"2"},{"word":"blot","freq":19,"score":156,"flags":"bc","syllables":"1"},{"word":"clot","freq":19,"score":156,"flags":"bc","syllables":"1"},{"word":"trot","freq":19,"score":156,"flags":"bc","syllables":"1"},{"word":"exert","freq":21,"score":156,"flags":"bc","syllables":"2"},{"word":"forgot","freq":21,"score":156,"flags":"bc","syllables":"2"},{"word":"insert","freq":21,"score":156,"flags":"bc","syllables":"2"},{"word":"divert","freq":20,"score":156,"flags":"bc","syllables":"2"},{"word":"dessert","freq":19,"score":156,"flags":"bc","syllables":"2"},{"word":"revert","freq":19,"score":156,"flags":"bc","syllables":"2"},{"word":"somewhat","freq":24,"score":156,"flags":"bc","syllables":"2"},{"word":"coconut","freq":19,"score":156,"flags":"bc","syllables":"3"}]