[
  {
    "name": "Mary Beth Alexander",
    "school": "nightingale",
    "title": "Music Faculty",
    "education": "BA, Vassar College",
    "email": "MBeth@thewinwardschool.org"
  },
  {
    "name": "Victoria Allison-Griffith",
    "school": "nightingale",
    "title": "Mathematics Faculty",
    "email": "VAllison-Griffith@thewinwardschool.org"
  },
  {
    "name": "Lauren Aloia",
    "school": "nightingale",
    "education": "M.M., Temple University, B.M., Temple University",
    "email": "LAloia@thewinwardschool.org"
  },
  {
    "name": "Niurka Alvarez",
    "school": "nightingale",
    "title": "Modern Languages Faculty",
    "education": "BA, Hunter College, MA, New York University",
    "email": "NAlvarez@thewinwardschool.org"
  },
  {
    "name": "Anna Marie Ambrose",
    "school": "nightingale",
    "title": "Lower School Assistant",
    "education": "BS, Fordham University",
    "email": "AMarie@thewinwardschool.org"
  },
  {
    "name": "Claire Anderson",
    "school": "nightingale",
    "title": "Associate Head of Lower School",
    "education": "AB, Kenyon College, MA, Bank Street College of Education",
    "email": "CAnderson@thewinwardschool.org"
  },
  {
    "name": "Julia Anderson",
    "school": "nightingale",
    "title": "Modern Languages Faculty",
    "education": "DEUG, Université de Paris",
    "email": "JAnderson@thewinwardschool.org"
  },
  {
    "name": "Abby Balafas",
    "school": "nightingale",
    "title": "Associate Director of Admissions; Director of Upper School Student Life",
    "education": "M.M., University of North Carolina at Greensboro, B.S., Virginia Tech",
    "email": "ABalafas@thewinwardschool.org"
  },
  {
    "name": "Peggy Balsam",
    "school": "nightingale",
    "title": "Assistant to Head of Upper School",
    "email": "PBalsam@thewinwardschool.org"
  },
  {
    "name": "Rebecca Barbato",
    "school": "nightingale",
    "title": "Head of Science Department",
    "education": "BS, Shenandoah University, MS, Old Dominion University",
    "email": "RBarbato@thewinwardschool.org"
  },
  {
    "name": "Amparo Baron",
    "school": "nightingale",
    "title": "Modern Languages Faculty",
    "education": "BA, Queen's College, MA, Queen's College",
    "email": "ABaron@thewinwardschool.org"
  },
  {
    "name": "Frank Barros",
    "school": "nightingale",
    "title": "Science Faculty",
    "education": "BA, College of Holy Cross, MFS, Yale University",
    "email": "FBarros@thewinwardschool.org"
  },
  {
    "name": "Katie Bednark",
    "school": "nightingale",
    "title": "School Archivist",
    "email": "KBednark@thewinwardschool.org"
  },
  {
    "name": "Nicole Bedoya",
    "school": "nightingale",
    "title": "Advancement Associate",
    "education": "Bachelor of Arts, Emmanuel College",
    "email": "NBedoya@thewinwardschool.org"
  },
  {
    "name": "Antoine Bell",
    "school": "nightingale",
    "title": "Security Officer",
    "email": "ABell@thewinwardschool.org"
  },
  {
    "name": "Ian Bell",
    "school": "nightingale",
    "title": "Artist in Residence",
    "education": "BA, Sarah Lawrence College, MFA, New York University",
    "email": "IBell@thewinwardschool.org"
  },
  {
    "name": "Heather Beveridge",
    "school": "nightingale",
    "title": "Director of College Counseling",
    "education": "BA, Smith College",
    "email": "HBeveridge@thewinwardschool.org"
  },
  {
    "name": "Allan Bikk",
    "school": "nightingale",
    "title": "History Faculty",
    "education": "BA, Binghamton University, MA, Columbia University\nMA, Teachers College",
    "email": "ABikk@thewinwardschool.org"
  },
  {
    "name": "Ruth Bodell",
    "school": "nightingale",
    "title": "Lower School Faculty",
    "education": "BA, Bowdoin College, MS Ed, Bank Street College of Education",
    "email": "RBodell@thewinwardschool.org"
  },
  {
    "name": "Craig Bolotin",
    "school": "nightingale",
    "title": "Data Systems Manager",
    "education": "M.Ed., Lehigh University, B.S., Lehigh University",
    "email": "CBolotin@thewinwardschool.org"
  },
  {
    "name": "Jamie Borowicz",
    "school": "nightingale",
    "title": "Middle School Technology Integrator",
    "education": "BA, University of Virginia, MT, University of Virginia",
    "email": "JBorowicz@thewinwardschool.org"
  },
  {
    "name": "Jennifer Brodsky",
    "school": "nightingale",
    "title": "Director of Admissions",
    "education": "A.B. 1985, Dartmouth College, Hanover, NH",
    "email": "JBrodsky@thewinwardschool.org"
  },
  {
    "name": "Emily Bronstein",
    "school": "nightingale",
    "title": "Director of Alumnae Relations",
    "education": "BA, Brandeis University, MA, Teachers College, Columbia University",
    "email": "EBronstein@thewinwardschool.org"
  },
  {
    "name": "Paul Burke",
    "school": "nightingale",
    "title": "Head of School",
    "education": "BA, Williams College, MA, Teachers College",
    "email": "PBurke@thewinwardschool.org"
  },
  {
    "name": "Courtney Bynoe",
    "school": "nightingale",
    "education": "Masters, St. Joseph's College, Bachelors, Farmingdale State College",
    "email": "CBynoe@thewinwardschool.org"
  },
  {
    "name": "Lisa Campbell",
    "school": "nightingale",
    "title": "Head of PE Department",
    "education": "BA, SUNY Cortland, MA, University of Phoenix",
    "email": "LCampbell@thewinwardschool.org"
  },
  {
    "name": "John Caputo",
    "school": "nightingale",
    "title": "Head of Mathematics Department",
    "education": "BS, New York University, Stern School of Business, MS, Brooklyn College (CUNY)",
    "email": "JCaputo@thewinwardschool.org"
  },
  {
    "name": "Amanda Cecil",
    "school": "nightingale",
    "title": "Director of Athletics",
    "education": "BA, Gettysburg College",
    "email": "ACecil@thewinwardschool.org"
  },
  {
    "name": "Pamela Charles",
    "school": "nightingale",
    "title": "PE Faculty",
    "education": "BS, Eastern Kentucky University, MA, Teachers College\nDC, Life University\nDACNB, Carrick Institute for Graduate Studies",
    "email": "PCharles@thewinwardschool.org"
  },
  {
    "name": "Robert Charlton",
    "school": "nightingale",
    "title": "Maintenance Staff",
    "email": "RCharlton@thewinwardschool.org"
  },
  {
    "name": "Tamisha Chestnut",
    "school": "nightingale",
    "title": "Director of Human Resources",
    "education": "BA, Hampton University, MS, Mercy College",
    "email": "TChestnut@thewinwardschool.org"
  },
  {
    "name": "Micaela Chiaramonte",
    "school": "nightingale",
    "title": "Director of Major Gifts/Centennial Coordinator",
    "education": "BA, College of the Holy Cross",
    "email": "MChiaramonte@thewinwardschool.org"
  },
  {
    "name": "Michelle Cocchiaro",
    "school": "nightingale",
    "title": "PE Faculty",
    "education": "BA, SUNY Cortland, MA, SUNY Stony Brook",
    "email": "MCocchiaro@thewinwardschool.org"
  },
  {
    "name": "Nicole Cohen",
    "school": "nightingale",
    "title": "Learning Specialist, Testing Coordinator Advisor",
    "education": "B.Ed / M.A, Cambridge University UK / Columbia University, NYC, MA, Teachers College",
    "email": "NCohen@thewinwardschool.org"
  },
  {
    "name": "Susan Cohen-Nicole",
    "school": "nightingale",
    "title": "Modern Languages Faculty",
    "education": "BA, Boston University, MA, Middlebury College\nPhD, New York University",
    "email": "SCohen-Nicole@thewinwardschool.org"
  },
  {
    "name": "Jeanine Cooley",
    "school": "nightingale",
    "title": "Learning Specialist",
    "education": "M. ED, Columbia University, MA, Teachers College",
    "email": "JCooley@thewinwardschool.org"
  },
  {
    "name": "Cynthia Coudert",
    "school": "nightingale",
    "title": "Associate Director of Drama Department",
    "education": "BA, Vassar College",
    "email": "CCoudert@thewinwardschool.org"
  },
  {
    "name": "Chela Crinnion",
    "school": "nightingale",
    "title": "Modern Languages Faculty",
    "email": "CCrinnion@thewinwardschool.org"
  },
  {
    "name": "Marisue Cummins",
    "school": "nightingale",
    "title": "Lower School Faculty",
    "education": "BS, University of Delaware, MA, New York University",
    "email": "MCummins@thewinwardschool.org"
  },
  {
    "name": "Joanna Curtis",
    "school": "nightingale",
    "title": "History Faculty",
    "education": "PhD, New York University, MSc, London School of Economics\nBA, Swarthmore College",
    "email": "JCurtis@thewinwardschool.org"
  },
  {
    "name": "Panayotes Dakouras",
    "school": "nightingale",
    "title": "Head of Classics Department",
    "education": "BA, University of Athens, MA, New York University\nPhD, New York University",
    "email": "PDakouras@thewinwardschool.org"
  },
  {
    "name": "Diane Davis",
    "school": "nightingale",
    "title": "Head of Drama Department",
    "education": "BA, Olivet College",
    "email": "DDavis@thewinwardschool.org"
  },
  {
    "name": "Denise DeBono",
    "school": "nightingale",
    "title": "Admissions Assistant",
    "email": "DDeBono@thewinwardschool.org"
  },
  {
    "name": "Candi Deschamps",
    "school": "nightingale",
    "title": "English Faculty",
    "education": "BA, Smith College, MA, Teachers College",
    "email": "CDeschamps@thewinwardschool.org"
  },
  {
    "name": "Angela Dewitt",
    "school": "nightingale",
    "title": "Security Officer",
    "email": "ADewitt@thewinwardschool.org"
  },
  {
    "name": "Laura Donaldson",
    "school": "nightingale",
    "title": "Lower School Faculty",
    "education": "BA, Hamilton College",
    "email": "LDonaldson@thewinwardschool.org"
  },
  {
    "name": "Mark Donovan",
    "school": "nightingale",
    "title": "Writing Specialist",
    "education": "BA, Williams College",
    "email": "MDonovan@thewinwardschool.org"
  },
  {
    "name": "Kristyn Dorfman",
    "school": "nightingale",
    "title": "Middle School Librarian",
    "email": "KDorfman@thewinwardschool.org"
  },
  {
    "name": "Claire du Nouy",
    "school": "nightingale",
    "title": "Associate Head of School; Head of Middle School",
    "education": "BA, Swarthmore College, MA, Teachers College",
    "email": "Cdu@thewinwardschool.org"
  },
  {
    "name": "Naomi Hayashi Eldredge",
    "school": "nightingale",
    "title": "Admissions Assistant",
    "education": "Bank Street College, BFA, New York University\nHighschool Diploma, Kentwood Highschool",
    "email": "NHayashi@thewinwardschool.org"
  },
  {
    "name": "Jena Epstein",
    "school": "nightingale",
    "title": "History Faculty",
    "education": "BA, Carleton College, MA, Teachers College",
    "email": "JEpstein@thewinwardschool.org"
  },
  {
    "name": "Alfonso Espinal",
    "school": "nightingale",
    "title": "Director of Technology",
    "education": "MS, Syracuse University, BS, Syracuse University",
    "email": "AEspinal@thewinwardschool.org"
  },
  {
    "name": "Amanda Espy",
    "school": "nightingale",
    "title": "Lower School Faculty",
    "education": "BA, George Washington University, MEd, New York University",
    "email": "AEspy@thewinwardschool.org"
  },
  {
    "name": "Elizabeth Fairbairn",
    "school": "nightingale",
    "title": "Science Faculty",
    "education": "BA, UC Santa Barbara, MA, University of Phoenix",
    "email": "EFairbairn@thewinwardschool.org"
  },
  {
    "name": "Hai Dan Fan",
    "school": "nightingale",
    "title": "Lower School Faculty",
    "education": "BS, Binghamton University",
    "email": "HDan@thewinwardschool.org"
  },
  {
    "name": "Elizabeth Fernandez",
    "school": "nightingale",
    "title": "Director of Library and Academic Resource Center",
    "education": "BA, New York University, MA, Hunter College\nMLS, Palmer School of Library and Information Science",
    "email": "EFernandez@thewinwardschool.org"
  },
  {
    "name": "Linda Field",
    "school": "nightingale",
    "title": "Scheduler; History Faculty",
    "education": "BA, Princeton University, MA, Teachers College",
    "email": "LField@thewinwardschool.org"
  },
  {
    "name": "Jeanne Finnigan-John",
    "school": "nightingale",
    "title": "PE Faculty; Dance Faculty",
    "education": "BS, University of Nebraska-Lincoln",
    "email": "JFinnigan-John@thewinwardschool.org"
  },
  {
    "name": "Todd Flomberg",
    "school": "nightingale",
    "title": "Science Faculty",
    "education": "BA, Binghamton University, MA, Teachers College",
    "email": "TFlomberg@thewinwardschool.org"
  },
  {
    "name": "Veronica Frenning",
    "school": "nightingale",
    "title": "Art Faculty",
    "email": "VFrenning@thewinwardschool.org"
  },
  {
    "name": "Sebnem Giorgio",
    "school": "nightingale",
    "email": "SGiorgio@thewinwardschool.org"
  },
  {
    "name": "Michael Goede",
    "school": "nightingale",
    "title": "Head of Music Department",
    "education": "Bachelor of Music Education, Bachelor of Arts, Valparaiso University, Master of Music, The Ohio State University",
    "email": "MGoede@thewinwardschool.org"
  },
  {
    "name": "Amanda Goodwin",
    "school": "nightingale",
    "title": "Associate Head of Middle School, Head of history department",
    "education": "BA, Middlebury College, MA, Columbia University",
    "email": "AGoodwin@thewinwardschool.org"
  },
  {
    "name": "Catherine Greco Higgins",
    "school": "nightingale",
    "title": "Associate Director of Finance",
    "education": "BS, CPA, SUNY Albany",
    "email": "CGreco@thewinwardschool.org"
  },
  {
    "name": "Chimene Green",
    "school": "nightingale",
    "title": "Admissions Coordinator",
    "email": "CGreen@thewinwardschool.org"
  },
  {
    "name": "Molly Grew",
    "school": "nightingale",
    "title": "Lower School Faculty",
    "email": "MGrew@thewinwardschool.org"
  },
  {
    "name": "Chloe Grimes",
    "school": "nightingale",
    "title": "Athletic Trainer",
    "education": "B.S., The University of Iowa",
    "email": "CGrimes@thewinwardschool.org"
  },
  {
    "name": "Cate Guimaraes",
    "school": "nightingale",
    "title": "Mathematics Faculty",
    "education": "Bachelor of Arts, Boston College, Masters of Science in Education, City College of New York (CUNY)",
    "email": "CGuimaraes@thewinwardschool.org"
  },
  {
    "name": "Christine Habib",
    "school": "nightingale",
    "title": "Science Faculty",
    "education": "BS, Haverford College",
    "email": "CHabib@thewinwardschool.org"
  },
  {
    "name": "Laura Hale",
    "school": "nightingale",
    "title": "Lower School Faculty",
    "education": "BA, Denison University, MAT, Simmons College",
    "email": "LHale@thewinwardschool.org"
  },
  {
    "name": "Kira Harris",
    "school": "nightingale",
    "title": "Art Faculty",
    "education": "BA, UC Santa Cruz, MFA, California Institute of the Arts",
    "email": "KHarris@thewinwardschool.org"
  },
  {
    "name": "L.E. Hartmann",
    "school": "nightingale",
    "title": "History Faculty",
    "education": "BA, Trinity College, MA, Brown University\nPhD, Brown University",
    "email": "LHartmann@thewinwardschool.org"
  },
  {
    "name": "Caroline Hastie",
    "school": "nightingale",
    "title": "Head of Art Department",
    "education": "BA, Sarah Lawrence College, MFA, Hunter College",
    "email": "CHastie@thewinwardschool.org"
  },
  {
    "name": "Kristen Healy",
    "school": "nightingale",
    "title": "Lower School Faculty",
    "education": "BA, Boston College, MA, Teacher's College, Columbia University",
    "email": "KHealy@thewinwardschool.org"
  },
  {
    "name": "Thomas Hein",
    "school": "nightingale",
    "title": "Director of Communications",
    "education": "BS, Fordham University, MBA, Fordham University",
    "email": "THein@thewinwardschool.org"
  },
  {
    "name": "Amy Helgeson",
    "school": "nightingale",
    "title": "Science Faculty",
    "education": "BS, University of Massachusetts, MA, Walden University",
    "email": "AHelgeson@thewinwardschool.org"
  },
  {
    "name": "Susan Heller",
    "school": "nightingale",
    "title": "Senior Advisor to the Dir. of Inst. Advancement",
    "education": "AAS, Bennett College, BS, Skidmore College",
    "email": "SHeller@thewinwardschool.org"
  },
  {
    "name": "Hannah Hens-Piazza",
    "school": "nightingale",
    "title": "Music Faculty; Director of Beyond the Classroom",
    "education": "BMus, New York University, MMus, New York University",
    "email": "HHens-Piazza@thewinwardschool.org"
  },
  {
    "name": "Teacher Hens-Piazza and Sealy",
    "school": "nightingale",
    "email": "THens-Piazza@thewinwardschool.org"
  },
  {
    "name": "Kathryn Hickey",
    "school": "nightingale",
    "email": "KHickey@thewinwardschool.org"
  },
  {
    "name": "Joel Hinds-Ortiz",
    "school": "nightingale",
    "title": "Chef Manager",
    "email": "JHinds-Ortiz@thewinwardschool.org"
  },
  {
    "name": "Chloe Houston",
    "school": "nightingale",
    "title": "Mathematics Faculty",
    "education": "BA, Bates College, MS, Long Island University",
    "email": "CHouston@thewinwardschool.org"
  },
  {
    "name": "Samuel Howell",
    "school": "nightingale",
    "title": "Co-Head of Modern Language Department; Classics Faculty",
    "education": "AB, Kenyon College, MA, University of Florida",
    "email": "SHowell@thewinwardschool.org"
  },
  {
    "name": "Robyn Jaffe",
    "school": "nightingale",
    "title": "Director of Health and Wellness",
    "email": "RJaffe@thewinwardschool.org"
  },
  {
    "name": "Christine Javier",
    "school": "nightingale",
    "title": "Director of Institutional Research",
    "education": "BA, Georgetown University, MPP, Harvard Kennedy School of Government",
    "email": "CJavier@thewinwardschool.org"
  },
  {
    "name": "Francine Jenkins",
    "school": "nightingale",
    "title": "Security Officer",
    "email": "FJenkins@thewinwardschool.org"
  },
  {
    "name": "Charlotte Jennings",
    "school": "nightingale",
    "title": "Associate Head of Upper School; Science Faculty, Science Faculty",
    "education": "Master of Science, University of Tennessee, MS, University of Tennessee",
    "email": "CJennings@thewinwardschool.org"
  },
  {
    "name": "Karen Joseloff",
    "school": "nightingale",
    "title": "Communications Associate",
    "email": "KJoseloff@thewinwardschool.org"
  },
  {
    "name": "Sarah Kadzakumanja",
    "school": "nightingale",
    "title": "Lower School Faculty",
    "education": "BA, University of Vermont",
    "email": "SKadzakumanja@thewinwardschool.org"
  },
  {
    "name": "Kristina Kalaw Joyas",
    "school": "nightingale",
    "title": "Operations Associate",
    "education": "BA, Stony Brook University, MS, Columbia University",
    "email": "KKalaw@thewinwardschool.org"
  },
  {
    "name": "Andrea Kassar",
    "school": "nightingale",
    "title": "Head of Upper School",
    "education": "BA, University of Chicago, MA, Columbia University\nMA, New School for Social Research",
    "email": "AKassar@thewinwardschool.org"
  },
  {
    "name": "Jeffrey Kearney",
    "school": "nightingale",
    "title": "Classics Faculty",
    "education": "BA, University of North Carolina, MA, University of North Carolina",
    "email": "JKearney@thewinwardschool.org"
  },
  {
    "name": "Kathleen Kernell",
    "school": "nightingale",
    "title": "Music Faculty",
    "education": "BA, Macalester College, Diplome d'Execution, Ecole Normale Superieure de Musique de Paris",
    "email": "KKernell@thewinwardschool.org"
  },
  {
    "name": "Laura Kirk",
    "school": "nightingale",
    "title": "English Faculty",
    "education": "BA, Wesleyan University, MFA, Mills College",
    "email": "LKirk@thewinwardschool.org"
  },
  {
    "name": "Alex Klikunas",
    "school": "nightingale",
    "title": "Co-Head of Modern Language Department",
    "education": "BA, Middlebury College",
    "email": "AKlikunas@thewinwardschool.org"
  },
  {
    "name": "Naomi Kohen",
    "school": "nightingale",
    "title": "Science Faculty",
    "education": "B.S., MIT, PhD, UC Berkeley",
    "email": "NKohen@thewinwardschool.org"
  },
  {
    "name": "Erica Lee",
    "school": "nightingale",
    "title": "Director of Annual Giving and Constituent Relations",
    "education": "BS, Bryant University",
    "email": "ELee@thewinwardschool.org"
  },
  {
    "name": "Salomon Lerner",
    "school": "nightingale",
    "title": "Music Faculty",
    "email": "SLerner@thewinwardschool.org"
  },
  {
    "name": "Lisa Levine",
    "school": "nightingale",
    "title": "School Nurse",
    "education": "BSN, University of Pennsylvania, MSN, Hunter College",
    "email": "LLevine@thewinwardschool.org"
  },
  {
    "name": "Jennifer Levitt",
    "school": "nightingale",
    "title": "English Faculty",
    "email": "JLevitt@thewinwardschool.org"
  },
  {
    "name": "Rachael Lewiton",
    "school": "nightingale",
    "title": "Middle School Counselor",
    "email": "RLewiton@thewinwardschool.org"
  },
  {
    "name": "Lily Liang",
    "school": "nightingale",
    "email": "LLiang@thewinwardschool.org"
  },
  {
    "name": "John Loughery",
    "school": "nightingale",
    "title": "English Faculty",
    "education": "BA, Fordham University",
    "email": "JLoughery@thewinwardschool.org"
  },
  {
    "name": "Claire Lulow",
    "school": "nightingale",
    "title": "Math Faculty",
    "education": "BS, BFA, University of Iowa",
    "email": "CLulow@thewinwardschool.org"
  },
  {
    "name": "Kornelia Luzaic",
    "school": "nightingale",
    "title": "Maintenance Staff",
    "email": "KLuzaic@thewinwardschool.org"
  },
  {
    "name": "Patricia Lynch",
    "school": "nightingale",
    "title": "Library Assistant",
    "email": "PLynch@thewinwardschool.org"
  },
  {
    "name": "Damaris Maclean",
    "school": "nightingale",
    "title": "Dir of Global Partnerships & Community Engagement",
    "education": "MEd, Teachers College Columbia University, MA, Middlebury College\nBA, Haverford College",
    "email": "DMaclean@thewinwardschool.org"
  },
  {
    "name": "Christopher Macmeikan",
    "school": "nightingale",
    "title": "Mathematics Faculty",
    "education": "PhD, University of Sydney, BS, University of Melbourne",
    "email": "CMacmeikan@thewinwardschool.org"
  },
  {
    "name": "Jasmine Maldonado",
    "school": "nightingale",
    "title": "Mathematics Faculty",
    "email": "JMaldonado@thewinwardschool.org"
  },
  {
    "name": "Marica Mayuzumi",
    "school": "nightingale",
    "title": "Lower School Faculty",
    "education": "BA, Simmons College, MAT, Simmons College",
    "email": "MMayuzumi@thewinwardschool.org"
  },
  {
    "name": "Sarah McConnell",
    "school": "nightingale",
    "title": "Classics Faculty",
    "education": "BA, Mount Holyoke College, MA, Columbia University",
    "email": "SMcConnell@thewinwardschool.org"
  },
  {
    "name": "Deborah McCray",
    "school": "nightingale",
    "title": "Business Office Associate",
    "education": "AAS, Ulster County College, BA, Bard College",
    "email": "DMcCray@thewinwardschool.org"
  },
  {
    "name": "Jennifer McFeely",
    "school": "nightingale",
    "title": "Director of Counseling",
    "education": "BA, Kirkland College, MSW, Rutgers University",
    "email": "JMcFeely@thewinwardschool.org"
  },
  {
    "name": "Rachel McKie",
    "school": "nightingale",
    "title": "Manager of Advancement Services",
    "education": "MA, Teachers College, Columbia University, BS, Cornell University",
    "email": "RMcKie@thewinwardschool.org"
  },
  {
    "name": "Catherine McMenamin",
    "school": "nightingale",
    "title": "English Faculty",
    "education": "BA, University of Notre Dame, MA, Columbia University",
    "email": "CMcMenamin@thewinwardschool.org"
  },
  {
    "name": "Scott Meikle",
    "school": "nightingale",
    "title": "Art Faculty",
    "education": "BA, Ringling School of Design, MFA, Louisiana State University",
    "email": "SMeikle@thewinwardschool.org"
  },
  {
    "name": "María Mergal",
    "school": "nightingale",
    "title": "Science Faculty, Lab Technician",
    "email": "MMergal@thewinwardschool.org"
  },
  {
    "name": "Jim Meury",
    "school": "nightingale",
    "title": "Director of Safety and Security",
    "education": "AS, Nassau Community College",
    "email": "JMeury@thewinwardschool.org"
  },
  {
    "name": "Rene Mitchell",
    "school": "nightingale",
    "title": "Associate Director of Annual Giving and Constituent Relations",
    "education": "BA, Southern Methodist University",
    "email": "RMitchell@thewinwardschool.org"
  },
  {
    "name": "Susan Mohi",
    "school": "nightingale",
    "title": "Director of Institutional Advancement",
    "education": "BS, Central Connecticut State University",
    "email": "SMohi@thewinwardschool.org"
  },
  {
    "name": "Vickie Monta",
    "school": "nightingale",
    "title": "Director of Finance",
    "education": "BS, Lesley University, MBA, Regis University",
    "email": "VMonta@thewinwardschool.org"
  },
  {
    "name": "Eddie Montenegro",
    "school": "nightingale",
    "title": "Associate Director of College Counseling",
    "email": "EMontenegro@thewinwardschool.org"
  },
  {
    "name": "Erin Morlock",
    "school": "nightingale",
    "title": "Art Faculty",
    "email": "EMorlock@thewinwardschool.org"
  },
  {
    "name": "The MS PE Faculty",
    "school": "nightingale",
    "email": "TMS@thewinwardschool.org"
  },
  {
    "name": "Marin Nass",
    "school": "nightingale",
    "email": "MNass@thewinwardschool.org"
  },
  {
    "name": "Elias Oquendo",
    "school": "nightingale",
    "title": "Maintenance Staff",
    "email": "EOquendo@thewinwardschool.org"
  },
  {
    "name": "Elizabeth Osborne",
    "school": "nightingale",
    "title": "English Faculty",
    "education": "BA, Harvard University, MFA, Columbia University",
    "email": "EOsborne@thewinwardschool.org"
  },
  {
    "name": "Karen Park",
    "school": "nightingale",
    "title": "Mathematics Faculty",
    "email": "KPark@thewinwardschool.org"
  },
  {
    "name": "Jennifer Pentecost",
    "school": "nightingale",
    "title": "Lower School Faculty",
    "email": "JPentecost@thewinwardschool.org"
  },
  {
    "name": "Abigail Perelman",
    "school": "nightingale",
    "title": "History Faculty",
    "email": "APerelman@thewinwardschool.org"
  },
  {
    "name": "Emily Peters",
    "school": "nightingale",
    "title": "Communications Manager",
    "education": "BA, Kenyon College, MFA, New York University",
    "email": "EPeters@thewinwardschool.org"
  },
  {
    "name": "Richard \"Ricky\" Piper",
    "school": "nightingale",
    "email": "R\"Ricky\"@thewinwardschool.org"
  },
  {
    "name": "Manisha Pohani",
    "school": "nightingale",
    "email": "MPohani@thewinwardschool.org"
  },
  {
    "name": "Manisha Pohani",
    "school": "nightingale",
    "email": "MPohani@thewinwardschool.org"
  },
  {
    "name": "Maya Popa",
    "school": "nightingale",
    "title": "English Faculty, Director of the Creative Writing Program",
    "education": "BA, Barnard College, MFA, New York University\nMA, Oxford University",
    "email": "MPopa@thewinwardschool.org"
  },
  {
    "name": "Annalise Porras",
    "school": "nightingale",
    "title": "Lower School FLES Coordinator",
    "email": "APorras@thewinwardschool.org"
  },
  {
    "name": "Sloane Quealy-Miner",
    "school": "nightingale",
    "title": "Assistant to the Head of School",
    "education": "BA, Fairfield University",
    "email": "SQuealy-Miner@thewinwardschool.org"
  },
  {
    "name": "Rosanne Quinn",
    "school": "nightingale",
    "title": "PE Faculty",
    "education": "BSEd, SUNY Brockport, MSEd, Hunter College",
    "email": "RQuinn@thewinwardschool.org"
  },
  {
    "name": "Aleksander Radovich",
    "school": "nightingale",
    "title": "Technology Support Specialist",
    "email": "ARadovich@thewinwardschool.org"
  },
  {
    "name": "Sarah Raslowsky",
    "school": "nightingale",
    "title": "Mathematics Faculty",
    "education": "BA, Brown University, MA, Rutgers University",
    "email": "SRaslowsky@thewinwardschool.org"
  },
  {
    "name": "Lisa Reda",
    "school": "nightingale",
    "title": "PE Faculty",
    "education": "BA, Manhattanville College, MPhysEd, Manhattanville College",
    "email": "LReda@thewinwardschool.org"
  },
  {
    "name": "Melissa Rice",
    "school": "nightingale",
    "title": "Lower School Faculty",
    "education": "BA, Swarthmore College, MS, Bank Street College of Education",
    "email": "MRice@thewinwardschool.org"
  },
  {
    "name": "Javier Rodriguez Fernandez",
    "school": "nightingale",
    "title": "Modern Languages Faculty",
    "email": "JRodriguez@thewinwardschool.org"
  },
  {
    "name": "Christine Rogers",
    "school": "nightingale",
    "title": "Associate Director of Admissions",
    "education": "BA, Stanford University, MA, University of California, Berkeley\nMA, University of North Carolina, Chapel Hill",
    "email": "CRogers@thewinwardschool.org"
  },
  {
    "name": "Bryan Rosen",
    "school": "nightingale",
    "title": "Head of Computer Science Department, Lower School Technology Integrator",
    "education": "BA, The Catholic University of America, MA, Teachers College, Columbia University",
    "email": "BRosen@thewinwardschool.org"
  },
  {
    "name": "Zahra Ruffin",
    "school": "nightingale",
    "title": "Assistant to Associate Head of School; Middle School Associate",
    "education": "B.A., Dartmouth College",
    "email": "ZRuffin@thewinwardschool.org"
  },
  {
    "name": "Megan Sadoff",
    "school": "nightingale",
    "title": "History Faculty",
    "education": "BA, Wesleyan University, MA, Ben Gurion University\nMA, Teachers College, Columbia University",
    "email": "MSadoff@thewinwardschool.org"
  },
  {
    "name": "Eileen Saguirer",
    "school": "nightingale",
    "title": "PE Faculty",
    "education": "BS, Penn State University, MA, Adelphi University",
    "email": "ESaguirer@thewinwardschool.org"
  },
  {
    "name": "Hernán Sánchez",
    "school": "nightingale",
    "title": "Modern Languages Faculty",
    "education": "BA, Pontifical University Madre y Maestra, MDiv, University of Saint Thomas",
    "email": "HSánchez@thewinwardschool.org"
  },
  {
    "name": "Jane Schapiro",
    "school": "nightingale",
    "title": "Classics Faculty",
    "education": "BA, Barnard College, MA, Teachers College",
    "email": "JSchapiro@thewinwardschool.org"
  },
  {
    "name": "Christine Schutt",
    "school": "nightingale",
    "email": "CSchutt@thewinwardschool.org"
  },
  {
    "name": "Johara Sealy",
    "school": "nightingale",
    "title": "Director of Diversity and Equity",
    "education": "BA, Bryn Mawr College, MA, New York University",
    "email": "JSealy@thewinwardschool.org"
  },
  {
    "name": "Nicole Seibert",
    "school": "nightingale",
    "title": "Science Faculty",
    "education": "BS, University of Memphis, MAT, Northern Arizona University",
    "email": "NSeibert@thewinwardschool.org"
  },
  {
    "name": "Claudia Shapiro",
    "school": "nightingale",
    "email": "CShapiro@thewinwardschool.org"
  },
  {
    "name": "Stacey Shen",
    "school": "nightingale",
    "title": "Lower School Faculty",
    "education": "BA, Binghamton University, MS, Bank Street College of Education",
    "email": "SShen@thewinwardschool.org"
  },
  {
    "name": "Ghansham Singh",
    "school": "nightingale",
    "title": "Maintenance Staff",
    "email": "GSingh@thewinwardschool.org"
  },
  {
    "name": "Meneshwar Singh",
    "school": "nightingale",
    "title": "Maintenance Staff",
    "email": "MSingh@thewinwardschool.org"
  },
  {
    "name": "Jia Situ",
    "school": "nightingale",
    "title": "Modern Languages Faculty",
    "education": "BA, Hunter College, MA, New York University",
    "email": "JSitu@thewinwardschool.org"
  },
  {
    "name": "Isabel Slokar",
    "school": "nightingale",
    "title": "Lower School Faculty",
    "education": "BA, Bates College, MA, Bank Street College of Education",
    "email": "ISlokar@thewinwardschool.org"
  },
  {
    "name": "Anita Smith",
    "school": "nightingale",
    "title": "Receptionist",
    "email": "ASmith@thewinwardschool.org"
  },
  {
    "name": "Sherwyn Smith",
    "school": "nightingale",
    "title": "English Faculty",
    "education": "BA, Connecticut College",
    "email": "SSmith@thewinwardschool.org"
  },
  {
    "name": "Mary Beth Spina",
    "school": "nightingale",
    "title": "Science Faculty",
    "education": "BA, Smith College, PhD, Mount Sinai School of Medicine",
    "email": "MBeth@thewinwardschool.org"
  },
  {
    "name": "Kate Theisz",
    "school": "nightingale",
    "title": "Lower School Faculty",
    "education": "BA, Fordham University, MS, Bank Street College of Education",
    "email": "KTheisz@thewinwardschool.org"
  },
  {
    "name": "Lucia Thomas",
    "school": "nightingale",
    "title": "Assistant Director of Admissions",
    "education": "BA, Boston College",
    "email": "LThomas@thewinwardschool.org"
  },
  {
    "name": "Alixandra Tillis",
    "school": "nightingale",
    "title": "Mathematics Faculty",
    "education": "BA, Emory University, MA, New York University",
    "email": "ATillis@thewinwardschool.org"
  },
  {
    "name": "Margaret Tobin",
    "school": "nightingale",
    "title": "Art Faculty",
    "education": "BFA, University of Colorado, Diploma, Scuola di Lorenzo di Medici\nMFA, Queens College",
    "email": "MTobin@thewinwardschool.org"
  },
  {
    "name": "Allison Trotta",
    "school": "nightingale",
    "title": "Head of Dance Department",
    "education": "BA, Marymount College, MFA, Sarah Lawrence College",
    "email": "ATrotta@thewinwardschool.org"
  },
  {
    "name": "Sara Turilli",
    "school": "nightingale",
    "title": "Music Faculty",
    "education": "BMus, The Catholic University of America, MA, New York University",
    "email": "STurilli@thewinwardschool.org"
  },
  {
    "name": "Gabriel Ulibarri",
    "school": "nightingale",
    "title": "History Faculty",
    "email": "GUlibarri@thewinwardschool.org"
  },
  {
    "name": "John Ulmer",
    "school": "nightingale",
    "title": "Director of Operations and Capital Management",
    "email": "JUlmer@thewinwardschool.org"
  },
  {
    "name": "Rebecca Urciuoli",
    "school": "nightingale",
    "title": "Head of Lower School",
    "education": "BA, Princeton University, EdM, Teachers College\nPhD, Columbia University",
    "email": "RUrciuoli@thewinwardschool.org"
  },
  {
    "name": "Talia Varonos-Pavlopoulos",
    "school": "nightingale",
    "title": "Classics Faculty",
    "education": "BA, Columbia University, MA, New York University",
    "email": "TVaronos-Pavlopoulos@thewinwardschool.org"
  },
  {
    "name": "Nikki Vivion",
    "school": "nightingale",
    "title": "Director of Strategic Initiatives; Science Faculty",
    "education": "MPH, UCLA, BS, UCLA",
    "email": "NVivion@thewinwardschool.org"
  },
  {
    "name": "Andrew Vo",
    "school": "nightingale",
    "title": "IT Systems and Hardware Support Specialist",
    "email": "AVo@thewinwardschool.org"
  },
  {
    "name": "Grace Wang",
    "school": "nightingale",
    "title": "Modern Languages Faculty",
    "education": "BA, Soochow University, MA, New York University",
    "email": "GWang@thewinwardschool.org"
  },
  {
    "name": "Chimé Wangdu",
    "school": "nightingale",
    "title": "PE Faculty; Assistant to Athletic Director, Assistant to Athletic Director",
    "education": "BPE, Jiwaji University, BA, Punjab University\nMEd, Springfield College",
    "email": "CWangdu@thewinwardschool.org"
  },
  {
    "name": "Margaret Ward",
    "school": "nightingale",
    "title": "Science Faculty",
    "education": "BA, Vanderbilt University",
    "email": "MWard@thewinwardschool.org"
  },
  {
    "name": "Evin Watson",
    "school": "nightingale",
    "title": "Computer Science Faculty",
    "education": "BFA, New York University, MA, Teachers College",
    "email": "EWatson@thewinwardschool.org"
  },
  {
    "name": "Megan Westman",
    "school": "nightingale",
    "title": "Lower School Librarian",
    "education": "BA, American University, MSLIS, Pratt Institute School of Information",
    "email": "MWestman@thewinwardschool.org"
  },
  {
    "name": "Bradley Whitehurst",
    "school": "nightingale",
    "title": "Head of English Department",
    "education": "BA, College of William and Mary, MA, Georgetown University\nMLit, Middlebury College",
    "email": "BWhitehurst@thewinwardschool.org"
  }
]